uvxt/__init__.py
uvxt/__main__.py
uvxt/cli.py
uvxt-0.1.3.dist-info/METADATA
uvxt-0.1.3.dist-info/WHEEL
uvxt-0.1.3.dist-info/entry_points.txt
uvxt-0.1.3.dist-info/top_level.txt
uvxt-0.1.3.dist-info/RECORD
