Metadata-Version: 2.1
Name: uvxt
Version: 0.1.3
Summary: The best tools for developers using uv
Author-email: Alekse Marusich <alekse.marusich@rocshers.com>
License: MIT
Keywords: rocshers,uvxt,uv,pypi
Classifier: License :: OSI Approved :: MIT License
Classifier: Intended Audience :: Developers
Classifier: Intended Audience :: Information Technology
Classifier: Intended Audience :: System Administrators
Classifier: Operating System :: OS Independent
Classifier: Topic :: Software Development :: Build Tools
Classifier: Topic :: Software Development :: Libraries :: Python Modules
Classifier: Topic :: Software Development :: Libraries
Classifier: Topic :: Software Development
Classifier: Topic :: System :: Archiving :: Packaging
Classifier: Topic :: System :: Installation/Setup
Classifier: Topic :: System :: Software Distribution
Classifier: Programming Language :: Python :: 3 :: Only
Classifier: Programming Language :: Python :: 3.12
Classifier: Programming Language :: Python :: 3
Classifier: Programming Language :: Python
Requires-Python: >=3.12
Requires-Dist: typer >=0.10
Requires-Dist: uv-audit >=0.1.2
Requires-Dist: uv-stats >=0.1.0
Requires-Dist: uv-up >=0.1.0
Requires-Dist: uv-version >=0.1.1
